setup.py
statistic_dictionary/__init__.py
statistic_dictionary/statistic_dictionary.py
statistic_dictionary.egg-info/PKG-INFO
statistic_dictionary.egg-info/SOURCES.txt
statistic_dictionary.egg-info/dependency_links.txt
statistic_dictionary.egg-info/not-zip-safe
statistic_dictionary.egg-info/top_level.txt