Metadata-Version: 1.0
Name: statistic-dictionary
Version: 0.1
Summary: Statistic functions
Home-page: UNKNOWN
Author: Pyae Phyo Kyaw
Author-email: pyaekyaw1571999@gmail.com
License: UNKNOWN
Platform: UNKNOWN
